{"name": "PV", "showOnLockScreen": true, "views": [{"type": "text", "body": "32.05|24.99|0.12 kWh\n0|0|250|10 W\n93%|-270|21:06\n13.1 kWh|0.00|0.00"}], "families": [{"family": "graphicCircular", "class": "CLKComplicationTemplateGraphicCircularStackText", "line1": "32.0", "line2": "93%%"}, {"family": "circularSmall", "class": "CLKComplicationTemplateCircularSmallStackText", "line1": "32.0", "line2": "93%%"}, {"family": "modularSmall", "class": "CLKComplicationTemplateModularSmallStackText", "line1": "32.0", "line2": "93%%"}, {"family": "modularLarge", "class": "CLKComplicationTemplateModularLargeStandardBody", "header": "32.05|24.99|0.12 kWh", "body1": "0|0|250|10 W", "body2": "93%|-270|21:06"}, {"family": "graphicCorner", "class": "CLKComplicationTemplateGraphicCornerStackText", "innerText": "2.8|0.1|21:06", "outerText": "32.0·93%%"}, {"family": "graphicBezel", "class": "CLKComplicationTemplateGraphicBezelCircularText", "line1": "13.1", "line2": "93%%", "text": "32.05|24.99|0.12 kWh"}, {"family": "utilitarianSmall", "class": "CLKComplicationTemplateUtilitarianSmallFlat", "text": "93%|-270|21:06"}, {"family": "utilitarianLarge", "class": "CLKComplicationTemplateUtilitarianLargeFlat", "text": "32.05|24.99|0.12 kWh"}, {"family": "graphicRectangular", "class": "CLKComplicationTemplateGraphicRectangularStandardBody", "header": "32.05|24.99|0.12 kWh", "body1": "0|0|250|10 W", "body2": "13.1|93%%|-270|21:06", "body3": "13.1 kWh|0.00|0.00"}]}