{"name": "PV", "showOnLockScreen": true, "views": [{"type": "text", "body": "6.98|2.15|0.08 kWh\n880|2950|0|2950 W\n100%|0|10:58\n1.6 kWh|935 W|0 W"}], "families": [{"family": "graphicCircular", "class": "CLKComplicationTemplateGraphicCircularStackText", "line1": "7.0", "line2": "100%%"}, {"family": "circularSmall", "class": "CLKComplicationTemplateCircularSmallStackText", "line1": "7.0", "line2": "100%%"}, {"family": "modularSmall", "class": "CLKComplicationTemplateModularSmallStackText", "line1": "7.0", "line2": "100%%"}, {"family": "modularLarge", "class": "CLKComplicationTemplateModularLargeStandardBody", "header": "6.98|2.15|0.08 kWh", "body1": "880|2950|0|2950 W", "body2": "100%|0|10:58"}, {"family": "graphicCorner", "class": "CLKComplicationTemplateGraphicCornerStackText", "innerText": "1.8|0.1|10:58", "outerText": "7.0·100%%"}, {"family": "graphicBezel", "class": "CLKComplicationTemplateGraphicBezelCircularText", "line1": "1.6", "line2": "100%%", "text": "6.98|2.15|0.08 kWh"}, {"family": "utilitarianSmall", "class": "CLKComplicationTemplateUtilitarianSmallFlat", "text": "100%|0|10:58"}, {"family": "utilitarianLarge", "class": "CLKComplicationTemplateUtilitarianLargeFlat", "text": "6.98|2.15|0.08 kWh"}, {"family": "graphicRectangular", "class": "CLKComplicationTemplateGraphicRectangularStandardBody", "header": "6.98|2.15|0.08 kWh", "body1": "880|2950|0|2950 W", "body2": "1.6|100%%|0|10:58", "body3": "1.6 kWh|935 W|0 W"}]}