{"name": "PV", "showOnLockScreen": true, "views": [{"type": "text", "body": "31.56|24.05|0.08 kWh\n2050|2250|0|2250 W\n98%|0|16:05\n11.2 kWh|2111 W|0 W"}], "families": [{"family": "graphicCircular", "class": "CLKComplicationTemplateGraphicCircularStackText", "line1": "31.6", "line2": "98%%"}, {"family": "circularSmall", "class": "CLKComplicationTemplateCircularSmallStackText", "line1": "31.6", "line2": "98%%"}, {"family": "modularSmall", "class": "CLKComplicationTemplateModularSmallStackText", "line1": "31.6", "line2": "98%%"}, {"family": "modularLarge", "class": "CLKComplicationTemplateModularLargeStandardBody", "header": "31.56|24.05|0.08 kWh", "body1": "2050|2250|0|2250 W", "body2": "98%|0|16:05"}, {"family": "graphicCorner", "class": "CLKComplicationTemplateGraphicCornerStackText", "innerText": "2.1|0.1|16:05", "outerText": "31.6·98%%"}, {"family": "graphicBezel", "class": "CLKComplicationTemplateGraphicBezelCircularText", "line1": "11.2", "line2": "98%%", "text": "31.56|24.05|0.08 kWh"}, {"family": "utilitarianSmall", "class": "CLKComplicationTemplateUtilitarianSmallFlat", "text": "98%|0|16:05"}, {"family": "utilitarianLarge", "class": "CLKComplicationTemplateUtilitarianLargeFlat", "text": "31.56|24.05|0.08 kWh"}, {"family": "graphicRectangular", "class": "CLKComplicationTemplateGraphicRectangularStandardBody", "header": "31.56|24.05|0.08 kWh", "body1": "2050|2250|0|2250 W", "body2": "11.2|98%%|0|16:05", "body3": "11.2 kWh|2111 W|0 W"}]}