{"name": "PV", "showOnLockScreen": true, "views": [{"type": "text", "body": "3.21|1.21|0.11 kWh\n600|420|0|30 W\n74%|390|10:28\n2.4 kWh|184 W|423 W"}], "families": [{"family": "graphicCircular", "class": "CLKComplicationTemplateGraphicCircularStackText", "line1": "3.21", "line2": "74%%"}, {"family": "circularSmall", "class": "CLKComplicationTemplateCircularSmallStackText", "line1": "3.21", "line2": "74%%"}, {"family": "modularSmall", "class": "CLKComplicationTemplateModularSmallStackText", "line1": "3.21", "line2": "74%%"}, {"family": "modularLarge", "class": "CLKComplicationTemplateModularLargeStandardBody", "header": "3.21|1.21|0.11 kWh", "body1": "600|420|0|30 W", "body2": "74%|390|10:28"}, {"family": "graphicCorner", "class": "CLKComplicationTemplateGraphicCornerStackText", "innerText": "3.21|1.21|0.11 kWh", "outerText": "74%%"}, {"family": "graphicBezel", "class": "CLKComplicationTemplateGraphicBezelCircularText", "line1": "2.4", "line2": "74%%", "text": "3.21|1.21|0.11 kWh"}, {"family": "utilitarianSmall", "class": "CLKComplicationTemplateUtilitarianSmallFlat", "text": "74%|390|10:28"}, {"family": "utilitarianLarge", "class": "CLKComplicationTemplateUtilitarianLargeFlat", "text": "3.21|1.21|0.11 kWh"}, {"family": "graphicRectangular", "class": "CLKComplicationTemplateGraphicRectangularStandardBody", "header": "3.21|1.21|0.11 kWh", "body1": "600|420|0|30 W", "body2": "2.4|74%%|390|10:28", "body3": "2.4 kWh|184 W|423 W"}]}