{"name": "PV", "showOnLockScreen": true, "views": [{"type": "text", "body": "9.17|4.36|0.31 kWh\n3280|6300|0|6300 W\n98%|0|13:03\n5.6 kWh|1208 W|2068 W"}], "families": [{"family": "graphicCircular", "class": "CLKComplicationTemplateGraphicCircularStackText", "line1": "9.2", "line2": "98%%"}, {"family": "circularSmall", "class": "CLKComplicationTemplateCircularSmallStackText", "line1": "9.2", "line2": "98%%"}, {"family": "modularSmall", "class": "CLKComplicationTemplateModularSmallStackText", "line1": "9.2", "line2": "98%%"}, {"family": "modularLarge", "class": "CLKComplicationTemplateModularLargeStandardBody", "header": "9.17|4.36|0.31 kWh", "body1": "3280|6300|0|6300 W", "body2": "98%|0|13:03"}, {"family": "graphicCorner", "class": "CLKComplicationTemplateGraphicCornerStackText", "innerText": "4.4|0.3|13:03", "outerText": "9.2·98%%"}, {"family": "graphicBezel", "class": "CLKComplicationTemplateGraphicBezelCircularText", "line1": "5.6", "line2": "98%%", "text": "9.17|4.36|0.31 kWh"}, {"family": "utilitarianSmall", "class": "CLKComplicationTemplateUtilitarianSmallFlat", "text": "98%|0|13:03"}, {"family": "utilitarianLarge", "class": "CLKComplicationTemplateUtilitarianLargeFlat", "text": "9.17|4.36|0.31 kWh"}, {"family": "graphicRectangular", "class": "CLKComplicationTemplateGraphicRectangularStandardBody", "header": "9.17|4.36|0.31 kWh", "body1": "3280|6300|0|6300 W", "body2": "5.6|98%%|0|13:03", "body3": "5.6 kWh|1208 W|2068 W"}]}