{"name": "PV", "showOnLockScreen": true, "views": [{"type": "text", "body": "0.0|0.87|0.03 kWh\n0|0|170|-20 W\n84%|-150|05:47\n0 kWh|0 W|10 W"}], "families": [{"family": "graphicCircular", "class": "CLKComplicationTemplateGraphicCircularStackText", "line1": "0.0", "line2": "84%%"}, {"family": "circularSmall", "class": "CLKComplicationTemplateCircularSmallStackText", "line1": "0.0", "line2": "84%%"}, {"family": "modularSmall", "class": "CLKComplicationTemplateModularSmallStackText", "line1": "0.0", "line2": "84%%"}, {"family": "modularLarge", "class": "CLKComplicationTemplateModularLargeStandardBody", "header": "0.0|0.87|0.03 kWh", "body1": "0|0|170|-20 W", "body2": "84%|-150|05:47"}, {"family": "graphicCorner", "class": "CLKComplicationTemplateGraphicCornerStackText", "innerText": "0.9|0.0|05:47", "outerText": "0.0·84%%"}, {"family": "graphicBezel", "class": "CLKComplicationTemplateGraphicBezelCircularText", "line1": "0", "line2": "84%%", "text": "0.0|0.87|0.03 kWh"}, {"family": "utilitarianSmall", "class": "CLKComplicationTemplateUtilitarianSmallFlat", "text": "84%|-150|05:47"}, {"family": "utilitarianLarge", "class": "CLKComplicationTemplateUtilitarianLargeFlat", "text": "0.0|0.87|0.03 kWh"}, {"family": "graphicRectangular", "class": "CLKComplicationTemplateGraphicRectangularStandardBody", "header": "0.0|0.87|0.03 kWh", "body1": "0|0|170|-20 W", "body2": "0|84%%|-150|05:47", "body3": "0 kWh|0 W|10 W"}]}