{"name": "PV", "showOnLockScreen": true, "views": [{"type": "text", "body": "2025-05-19 11:37\nProd All: 12.79 kWh\nProd S1: 9.19 kWh\nProd S2: 3.6 kWh\nCon|Pur: 4.68|0.30 kWh\nFeed-in: 4.45 kWh\nPV1|PV2: 640|1640 W\nPV3: 1140 W\nP|C|G: 3440|0|3440 W\nBattery: 98%(0 W)\nCh|Dis: 6.50|4.13 kWh"}], "families": [{"family": "graphicCircular", "class": "CLKComplicationTemplateGraphicCircularStackText", "line1": "12.8", "line2": "98%%"}, {"family": "circularSmall", "class": "CLKComplicationTemplateCircularSmallStackText", "line1": "12.8", "line2": "98%%"}, {"family": "modularSmall", "class": "CLKComplicationTemplateModularSmallStackText", "line1": "12.8", "line2": "98%%"}, {"family": "modularLarge", "class": "CLKComplicationTemplateModularLargeStandardBody", "header": "12.79|4.45|0.30 kWh", "body1": "1140|2280|0|3440 W", "body2": "98%|0|11:37"}, {"family": "graphicCorner", "class": "CLKComplicationTemplateGraphicCornerStackText", "innerText": "4.7|0.3|11:37", "outerText": "12.8·98%%"}, {"family": "graphicBezel", "class": "CLKComplicationTemplateGraphicBezelCircularText", "line1": "3.6", "line2": "98%%", "text": "12.79|4.45|0.30 kWh"}, {"family": "utilitarianSmall", "class": "CLKComplicationTemplateUtilitarianSmallFlat", "text": "98%|0|11:37"}, {"family": "utilitarianLarge", "class": "CLKComplicationTemplateUtilitarianLargeFlat", "text": "12.79|4.45|0.30 kWh"}, {"family": "graphicRectangular", "class": "CLKComplicationTemplateGraphicRectangularStandardBody", "header": "12.79|4.45|0.30 kWh", "body1": "1140|2280|0|3440 W", "body2": "3.6|98%%|0|11:37", "body3": "3.6 kWh|640.00|1640.00"}]}