{"name": "PV", "showOnLockScreen": true, "views": [{"type": "text", "body": "2025-10-27 19:09\nProd All: 12.02 kWh\nProd S1: 7.82 kWh\nProd S2: 4.2 kWh\nCon|Pur: 5.14|6.37 kWh\nFeed-in: 9.98 kWh\nPV1|PV2: 0|0 W\nPV3: 0 W\nP|C|G: 0|150|0 W\nBattery: 95%(-150 W)\nCh|Dis: 2.86|0.99 kWh"}], "families": [{"family": "graphicCircular", "class": "CLKComplicationTemplateGraphicCircularStackText", "line1": "12.0", "line2": "95%%"}, {"family": "circularSmall", "class": "CLKComplicationTemplateCircularSmallStackText", "line1": "12.0", "line2": "95%%"}, {"family": "modularSmall", "class": "CLKComplicationTemplateModularSmallStackText", "line1": "12.0", "line2": "95%%"}, {"family": "modularLarge", "class": "CLKComplicationTemplateModularLargeStandardBody", "header": "12.02|9.98|6.37 kWh", "body1": "0|0|150|0 W", "body2": "95%|-150|19:09"}, {"family": "graphicCorner", "class": "CLKComplicationTemplateGraphicCornerStackText", "innerText": "5.1|6.4|19:09", "outerText": "12.0·95%%"}, {"family": "graphicBezel", "class": "CLKComplicationTemplateGraphicBezelCircularText", "line1": "4.2", "line2": "95%%", "text": "12.02|9.98|6.37 kWh"}, {"family": "utilitarianSmall", "class": "CLKComplicationTemplateUtilitarianSmallFlat", "text": "95%|-150|19:09"}, {"family": "utilitarianLarge", "class": "CLKComplicationTemplateUtilitarianLargeFlat", "text": "12.02|9.98|6.37 kWh"}, {"family": "graphicRectangular", "class": "CLKComplicationTemplateGraphicRectangularStandardBody", "header": "12.02|9.98|6.37 kWh", "body1": "0|0|150|0 W", "body2": "4.2|95%%|-150|19:09", "body3": "4.2 kWh|0.00|0.00"}]}