{"name": "PV", "showOnLockScreen": true, "views": [{"type": "text", "body": "0.28|1.10|0.08 kWh\n210|130|0|-20 W\n76%|150|08:07\n0.2 kWh|77 W|156 W"}], "families": [{"family": "graphicCircular", "class": "CLKComplicationTemplateGraphicCircularStackText", "line1": "0.3", "line2": "76%%"}, {"family": "circularSmall", "class": "CLKComplicationTemplateCircularSmallStackText", "line1": "0.3", "line2": "76%%"}, {"family": "modularSmall", "class": "CLKComplicationTemplateModularSmallStackText", "line1": "0.3", "line2": "76%%"}, {"family": "modularLarge", "class": "CLKComplicationTemplateModularLargeStandardBody", "header": "0.28|1.10|0.08 kWh", "body1": "210|130|0|-20 W", "body2": "76%|150|08:07"}, {"family": "graphicCorner", "class": "CLKComplicationTemplateGraphicCornerStackText", "innerText": "1.1|0.1|08:07", "outerText": "0.3·76%%"}, {"family": "graphicBezel", "class": "CLKComplicationTemplateGraphicBezelCircularText", "line1": "0.2", "line2": "76%%", "text": "0.28|1.10|0.08 kWh"}, {"family": "utilitarianSmall", "class": "CLKComplicationTemplateUtilitarianSmallFlat", "text": "76%|150|08:07"}, {"family": "utilitarianLarge", "class": "CLKComplicationTemplateUtilitarianLargeFlat", "text": "0.28|1.10|0.08 kWh"}, {"family": "graphicRectangular", "class": "CLKComplicationTemplateGraphicRectangularStandardBody", "header": "0.28|1.10|0.08 kWh", "body1": "210|130|0|-20 W", "body2": "0.2|76%%|150|08:07", "body3": "0.2 kWh|77 W|156 W"}]}