{"name": "PV", "showOnLockScreen": true, "views": [{"type": "text", "body": "2024-06-17 11:03\nProd All: 16.68 kWh\nProd S1: 14.48 kWh\nProd S2: 2.2 kWh\nCon|Pur: 4.78|0.29 kWh\nFeed-in: 8.84 kWh\nPV1|PV2: 660|3180 W\nPV3: 1880 W\nP|C|G: 5510|0|5510 W\nBattery: 97%(0 W)\nCh|Dis: 5.80|3.76 kWh"}], "families": [{"family": "graphicCircular", "class": "CLKComplicationTemplateGraphicCircularStackText", "line1": "16.7", "line2": "97%%"}, {"family": "circularSmall", "class": "CLKComplicationTemplateCircularSmallStackText", "line1": "16.7", "line2": "97%%"}, {"family": "modularSmall", "class": "CLKComplicationTemplateModularSmallStackText", "line1": "16.7", "line2": "97%%"}, {"family": "modularLarge", "class": "CLKComplicationTemplateModularLargeStandardBody", "header": "16.68|8.84|0.29 kWh", "body1": "1880|3840|0|5510 W", "body2": "97%|0|11:03"}, {"family": "graphicCorner", "class": "CLKComplicationTemplateGraphicCornerStackText", "innerText": "4.8|0.3|11:03", "outerText": "16.7·97%%"}, {"family": "graphicBezel", "class": "CLKComplicationTemplateGraphicBezelCircularText", "line1": "2.2", "line2": "97%%", "text": "16.68|8.84|0.29 kWh"}, {"family": "utilitarianSmall", "class": "CLKComplicationTemplateUtilitarianSmallFlat", "text": "97%|0|11:03"}, {"family": "utilitarianLarge", "class": "CLKComplicationTemplateUtilitarianLargeFlat", "text": "16.68|8.84|0.29 kWh"}, {"family": "graphicRectangular", "class": "CLKComplicationTemplateGraphicRectangularStandardBody", "header": "16.68|8.84|0.29 kWh", "body1": "1880|3840|0|5510 W", "body2": "2.2|97%%|0|11:03", "body3": "2.2 kWh|660.00|3180.00"}]}