{"name": "PV", "showOnLockScreen": true, "views": [{"type": "text", "body": "2024-08-29 15:57\nProd All: 30.65 kWh\nProd S1: 20.65 kWh\nProd S2: 10.0 kWh\nCon|Pur: 2.00|0.09 kWh\nFeed-in: 23.91 kWh\nPV1|PV2: 300|610 W\nPV3: 2720 W\nP|C|G: 820|800|20 W\nBattery: 97%(0 W)\nCh|Dis: 4.30|1.83 kWh"}], "families": [{"family": "graphicCircular", "class": "CLKComplicationTemplateGraphicCircularStackText", "line1": "30.6", "line2": "97%%"}, {"family": "circularSmall", "class": "CLKComplicationTemplateCircularSmallStackText", "line1": "30.6", "line2": "97%%"}, {"family": "modularSmall", "class": "CLKComplicationTemplateModularSmallStackText", "line1": "30.6", "line2": "97%%"}, {"family": "modularLarge", "class": "CLKComplicationTemplateModularLargeStandardBody", "header": "30.65|23.91|0.09 kWh", "body1": "2720|910|800|20 W", "body2": "97%|0|15:57"}, {"family": "graphicCorner", "class": "CLKComplicationTemplateGraphicCornerStackText", "innerText": "2.0|0.1|15:57", "outerText": "30.6·97%%"}, {"family": "graphicBezel", "class": "CLKComplicationTemplateGraphicBezelCircularText", "line1": "10.0", "line2": "97%%", "text": "30.65|23.91|0.09 kWh"}, {"family": "utilitarianSmall", "class": "CLKComplicationTemplateUtilitarianSmallFlat", "text": "97%|0|15:57"}, {"family": "utilitarianLarge", "class": "CLKComplicationTemplateUtilitarianLargeFlat", "text": "30.65|23.91|0.09 kWh"}, {"family": "graphicRectangular", "class": "CLKComplicationTemplateGraphicRectangularStandardBody", "header": "30.65|23.91|0.09 kWh", "body1": "2720|910|800|20 W", "body2": "10.0|97%%|0|15:57", "body3": "10.0 kWh|300.00|610.00"}]}