{"name": "PV", "showOnLockScreen": true, "views": [{"type": "text", "body": "2024-08-28 12:06\nProd All: 11.0 kWh\nProd S1: 7.70 kWh\nProd S2: 3.3 kWh\nCon|Pur: 1.71|0.10 kWh\nFeed-in: 6.32 kWh\nPV1|PV2: 710|2510 W\nPV3: 2370 W\nP|C|G: 3640|0|5830 W\nBattery: 98%(0 W)\nCh|Dis: 4.00|1.80 kWh"}], "families": [{"family": "graphicCircular", "class": "CLKComplicationTemplateGraphicCircularStackText", "line1": "11.0", "line2": "98%%"}, {"family": "circularSmall", "class": "CLKComplicationTemplateCircularSmallStackText", "line1": "11.0", "line2": "98%%"}, {"family": "modularSmall", "class": "CLKComplicationTemplateModularSmallStackText", "line1": "11.0", "line2": "98%%"}, {"family": "modularLarge", "class": "CLKComplicationTemplateModularLargeStandardBody", "header": "11.0|6.32|0.10 kWh", "body1": "2370|3220|0|5830 W", "body2": "98%|0|12:06"}, {"family": "graphicCorner", "class": "CLKComplicationTemplateGraphicCornerStackText", "innerText": "1.7|0.1|12:06", "outerText": "11.0·98%%"}, {"family": "graphicBezel", "class": "CLKComplicationTemplateGraphicBezelCircularText", "line1": "3.3", "line2": "98%%", "text": "11.0|6.32|0.10 kWh"}, {"family": "utilitarianSmall", "class": "CLKComplicationTemplateUtilitarianSmallFlat", "text": "98%|0|12:06"}, {"family": "utilitarianLarge", "class": "CLKComplicationTemplateUtilitarianLargeFlat", "text": "11.0|6.32|0.10 kWh"}, {"family": "graphicRectangular", "class": "CLKComplicationTemplateGraphicRectangularStandardBody", "header": "11.0|6.32|0.10 kWh", "body1": "2370|3220|0|5830 W", "body2": "3.3|98%%|0|12:06", "body3": "3.3 kWh|710.00|2510.00"}]}