{"name": "Reading", "showOnLockScreen": true, "views": [{"type": "text", "body": "Reading 1034.1hPa↑\n0.1°|98%|-6.3°|1.6°\n↘1|↘2|0.0(0.0)|17:17"}], "families": [{"family": "graphicCircular", "class": "CLKComplicationTemplateGraphicCircularStackText", "line1": "0.1°", "line2": "98%%"}, {"family": "circularSmall", "class": "CLKComplicationTemplateCircularSmallStackText", "line1": "0.1°", "line2": "98%"}, {"family": "modularSmall", "class": "CLKComplicationTemplateModularSmallStackText", "line1": "0.1°", "line2": "98%"}, {"family": "modularLarge", "class": "CLKComplicationTemplateModularLargeStandardBody", "header": "Reading 1034.1hPa↑", "body1": "0.1°|98%%|-6.3°|1.6°", "body2": "↘1|↘2|0.0(0.0)|17:17"}, {"family": "graphicCorner", "class": "CLKComplicationTemplateGraphicCornerStackText", "innerText": "↘1·↘2·17:17", "outerText": "0.1°·98%%"}, {"family": "graphicBezel", "class": "CLKComplicationTemplateGraphicBezelCircularText", "line1": "-6.3°", "line2": "1.6°", "text": "Reading 0.1°·98%%·↘1·↘2·17:17"}, {"family": "utilitarianSmall", "class": "CLKComplicationTemplateUtilitarianSmallFlat", "text": "0.1°·98%"}, {"family": "utilitarianLarge", "class": "CLKComplicationTemplateUtilitarianLargeFlat", "text": "Reading 0.1°·98%%·↘1·↘2·17:17"}, {"family": "graphicRectangular", "class": "CLKComplicationTemplateGraphicRectangularStandardBody", "header": "Reading 1034.1hPa↑", "body1": "0.1°|98%%|-6.3°|1.6°", "body2": "↘1|↘2|0.0(0.0)|17:17"}]}