{"name": "Reading", "showOnLockScreen": true, "views": [{"type": "text", "body": "Reading 1007.8hPa‚ÜĎ\n5¬į|89%|5¬į|7.8¬į\n‚Üí3|‚Üė8|0.3(0.3)|07:34"}], "families": [{"family": "graphicCircular", "class": "CLKComplicationTemplateGraphicCircularStackText", "line1": "5¬į", "line2": "89%%"}, {"family": "circularSmall", "class": "CLKComplicationTemplateCircularSmallStackText", "line1": "5¬į", "line2": "89%"}, {"family": "modularSmall", "class": "CLKComplicationTemplateModularSmallStackText", "line1": "5¬į", "line2": "89%"}, {"family": "modularLarge", "class": "CLKComplicationTemplateModularLargeStandardBody", "header": "Reading 1007.8hPa‚ÜĎ", "body1": "5¬į|89%%|5¬į|7.8¬į", "body2": "‚Üí3|‚Üė8|0.3(0.3)|07:34"}, {"family": "graphicCorner", "class": "CLKComplicationTemplateGraphicCornerStackText", "innerText": "‚Üí3¬∑‚Üė8¬∑07:34", "outerText": "5¬į¬∑89%%"}, {"family": "graphicBezel", "class": "CLKComplicationTemplateGraphicBezelCircularText", "line1": "5¬į", "line2": "7.8¬į", "text": "Reading 5¬į¬∑89%%¬∑‚Üí3¬∑‚Üė8¬∑07:34"}, {"family": "utilitarianSmall", "class": "CLKComplicationTemplateUtilitarianSmallFlat", "text": "5¬į¬∑89%"}, {"family": "utilitarianLarge", "class": "CLKComplicationTemplateUtilitarianLargeFlat", "text": "Reading 5¬į¬∑89%%¬∑‚Üí3¬∑‚Üė8¬∑07:34"}, {"family": "graphicRectangular", "class": "CLKComplicationTemplateGraphicRectangularStandardBody", "header": "Reading 1007.8hPa‚ÜĎ", "body1": "5¬į|89%%|5¬į|7.8¬į", "body2": "‚Üí3|‚Üė8|0.3(0.3)|07:34"}]}