{"name": "Reading", "showOnLockScreen": true, "views": [{"type": "text", "body": "Reading 1022hPa↔\n8°|49%|-0.4°|9.4°\n←3|←9|0.0(0.0)|17:09"}], "families": [{"family": "graphicCircular", "class": "CLKComplicationTemplateGraphicCircularStackText", "line1": "8°", "line2": "49%%"}, {"family": "circularSmall", "class": "CLKComplicationTemplateCircularSmallStackText", "line1": "8°", "line2": "49%"}, {"family": "modularSmall", "class": "CLKComplicationTemplateModularSmallStackText", "line1": "8°", "line2": "49%"}, {"family": "modularLarge", "class": "CLKComplicationTemplateModularLargeStandardBody", "header": "Reading 1022hPa↔", "body1": "8°|49%%|-0.4°|9.4°", "body2": "←3|←9|0.0(0.0)|17:09"}, {"family": "graphicCorner", "class": "CLKComplicationTemplateGraphicCornerStackText", "innerText": "←3·←9·17:09", "outerText": "8°·49%%"}, {"family": "graphicBezel", "class": "CLKComplicationTemplateGraphicBezelCircularText", "line1": "-0.4°", "line2": "9.4°", "text": "Reading 8°·49%%·←3·←9·17:09"}, {"family": "utilitarianSmall", "class": "CLKComplicationTemplateUtilitarianSmallFlat", "text": "8°·49%"}, {"family": "utilitarianLarge", "class": "CLKComplicationTemplateUtilitarianLargeFlat", "text": "Reading 8°·49%%·←3·←9·17:09"}, {"family": "graphicRectangular", "class": "CLKComplicationTemplateGraphicRectangularStandardBody", "header": "Reading 1022hPa↔", "body1": "8°|49%%|-0.4°|9.4°", "body2": "←3|←9|0.0(0.0)|17:09"}]}