{"name": "Reading", "showOnLockScreen": true, "views": [{"type": "text", "body": "Reading 976.5hPa↑\n9.6°|80%|8.6°|11.2°\n↗2|↑5|17.0(0.0)|23:19"}], "families": [{"family": "graphicCircular", "class": "CLKComplicationTemplateGraphicCircularStackText", "line1": "9.6°", "line2": "80%%"}, {"family": "circularSmall", "class": "CLKComplicationTemplateCircularSmallStackText", "line1": "9.6°", "line2": "80%"}, {"family": "modularSmall", "class": "CLKComplicationTemplateModularSmallStackText", "line1": "9.6°", "line2": "80%"}, {"family": "modularLarge", "class": "CLKComplicationTemplateModularLargeStandardBody", "header": "Reading 976.5hPa↑", "body1": "9.6°|80%%|8.6°|11.2°", "body2": "↗2|↑5|17.0(0.0)|23:19"}, {"family": "graphicCorner", "class": "CLKComplicationTemplateGraphicCornerStackText", "innerText": "↗2·↑5·23:19", "outerText": "9.6°·80%%"}, {"family": "graphicBezel", "class": "CLKComplicationTemplateGraphicBezelCircularText", "line1": "8.6°", "line2": "11.2°", "text": "Reading 9.6°·80%%·↗2·↑5·23:19"}, {"family": "utilitarianSmall", "class": "CLKComplicationTemplateUtilitarianSmallFlat", "text": "9.6°·80%"}, {"family": "utilitarianLarge", "class": "CLKComplicationTemplateUtilitarianLargeFlat", "text": "Reading 9.6°·80%%·↗2·↑5·23:19"}, {"family": "graphicRectangular", "class": "CLKComplicationTemplateGraphicRectangularStandardBody", "header": "Reading 976.5hPa↑", "body1": "9.6°|80%%|8.6°|11.2°", "body2": "↗2|↑5|17.0(0.0)|23:19"}]}