{"name": "Reading", "showOnLockScreen": true, "views": [{"type": "text", "body": "Reading 1004.1hPa↔\n14.8°|80%|10.7°|19°\n→2|↘5|1.8(0.0)|17:57"}], "families": [{"family": "graphicCircular", "class": "CLKComplicationTemplateGraphicCircularStackText", "line1": "14.8°", "line2": "80%%"}, {"family": "circularSmall", "class": "CLKComplicationTemplateCircularSmallStackText", "line1": "14.8°", "line2": "80%"}, {"family": "modularSmall", "class": "CLKComplicationTemplateModularSmallStackText", "line1": "14.8°", "line2": "80%"}, {"family": "modularLarge", "class": "CLKComplicationTemplateModularLargeStandardBody", "header": "Reading 1004.1hPa↔", "body1": "14.8°|80%%|10.7°|19°", "body2": "→2|↘5|1.8(0.0)|17:57"}, {"family": "graphicCorner", "class": "CLKComplicationTemplateGraphicCornerStackText", "innerText": "→2·↘5·17:57", "outerText": "14.8°·80%%"}, {"family": "graphicBezel", "class": "CLKComplicationTemplateGraphicBezelCircularText", "line1": "10.7°", "line2": "19°", "text": "Reading 14.8°·80%%·→2·↘5·17:57"}, {"family": "utilitarianSmall", "class": "CLKComplicationTemplateUtilitarianSmallFlat", "text": "14.8°·80%"}, {"family": "utilitarianLarge", "class": "CLKComplicationTemplateUtilitarianLargeFlat", "text": "Reading 14.8°·80%%·→2·↘5·17:57"}, {"family": "graphicRectangular", "class": "CLKComplicationTemplateGraphicRectangularStandardBody", "header": "Reading 1004.1hPa↔", "body1": "14.8°|80%%|10.7°|19°", "body2": "→2|↘5|1.8(0.0)|17:57"}]}