{"name": "Reading", "showOnLockScreen": true, "views": [{"type": "text", "body": "Reading 1000.1hPa↔\n11.3°|81%|3.5°|11.4°\n→7|↘14|0.0(0.0)|13:57"}], "families": [{"family": "graphicCircular", "class": "CLKComplicationTemplateGraphicCircularStackText", "line1": "11.3°", "line2": "81%%"}, {"family": "circularSmall", "class": "CLKComplicationTemplateCircularSmallStackText", "line1": "11.3°", "line2": "81%"}, {"family": "modularSmall", "class": "CLKComplicationTemplateModularSmallStackText", "line1": "11.3°", "line2": "81%"}, {"family": "modularLarge", "class": "CLKComplicationTemplateModularLargeStandardBody", "header": "Reading 1000.1hPa↔", "body1": "11.3°|81%%|3.5°|11.4°", "body2": "→7|↘14|0.0(0.0)|13:57"}, {"family": "graphicCorner", "class": "CLKComplicationTemplateGraphicCornerStackText", "innerText": "→7·↘14·13:57", "outerText": "11.3°·81%%"}, {"family": "graphicBezel", "class": "CLKComplicationTemplateGraphicBezelCircularText", "line1": "3.5°", "line2": "11.4°", "text": "Reading 11.3°·81%%·→7·↘14·13:57"}, {"family": "utilitarianSmall", "class": "CLKComplicationTemplateUtilitarianSmallFlat", "text": "11.3°·81%"}, {"family": "utilitarianLarge", "class": "CLKComplicationTemplateUtilitarianLargeFlat", "text": "Reading 11.3°·81%%·→7·↘14·13:57"}, {"family": "graphicRectangular", "class": "CLKComplicationTemplateGraphicRectangularStandardBody", "header": "Reading 1000.1hPa↔", "body1": "11.3°|81%%|3.5°|11.4°", "body2": "→7|↘14|0.0(0.0)|13:57"}]}