{"name": "Reading", "showOnLockScreen": true, "views": [{"type": "text", "body": "Reading 1010.4hPa↔\n20.6°|84%|18.8°|22.2°\n↖1|↖4|0.4(0.0)|18:17"}], "families": [{"family": "graphicCircular", "class": "CLKComplicationTemplateGraphicCircularStackText", "line1": "20.6°", "line2": "84%%"}, {"family": "circularSmall", "class": "CLKComplicationTemplateCircularSmallStackText", "line1": "20.6°", "line2": "84%"}, {"family": "modularSmall", "class": "CLKComplicationTemplateModularSmallStackText", "line1": "20.6°", "line2": "84%"}, {"family": "modularLarge", "class": "CLKComplicationTemplateModularLargeStandardBody", "header": "Reading 1010.4hPa↔", "body1": "20.6°|84%%|18.8°|22.2°", "body2": "↖1|↖4|0.4(0.0)|18:17"}, {"family": "graphicCorner", "class": "CLKComplicationTemplateGraphicCornerStackText", "innerText": "↖1·↖4·18:17", "outerText": "20.6°·84%%"}, {"family": "graphicBezel", "class": "CLKComplicationTemplateGraphicBezelCircularText", "line1": "18.8°", "line2": "22.2°", "text": "Reading 20.6°·84%%·↖1·↖4·18:17"}, {"family": "utilitarianSmall", "class": "CLKComplicationTemplateUtilitarianSmallFlat", "text": "20.6°·84%"}, {"family": "utilitarianLarge", "class": "CLKComplicationTemplateUtilitarianLargeFlat", "text": "Reading 20.6°·84%%·↖1·↖4·18:17"}, {"family": "graphicRectangular", "class": "CLKComplicationTemplateGraphicRectangularStandardBody", "header": "Reading 1010.4hPa↔", "body1": "20.6°|84%%|18.8°|22.2°", "body2": "↖1|↖4|0.4(0.0)|18:17"}]}