{"name": "Reading", "showOnLockScreen": true, "views": [{"type": "text", "body": "Reading 1012.1hPa↓\n11.1°|87%|10.5°|11.1°\n↗2|↗6|0.0(0.0)|04:30"}], "families": [{"family": "graphicCircular", "class": "CLKComplicationTemplateGraphicCircularStackText", "line1": "11.1°", "line2": "87%%"}, {"family": "circularSmall", "class": "CLKComplicationTemplateCircularSmallStackText", "line1": "11.1°", "line2": "87%"}, {"family": "modularSmall", "class": "CLKComplicationTemplateModularSmallStackText", "line1": "11.1°", "line2": "87%"}, {"family": "modularLarge", "class": "CLKComplicationTemplateModularLargeStandardBody", "header": "Reading 1012.1hPa↓", "body1": "11.1°|87%%|10.5°|11.1°", "body2": "↗2|↗6|0.0(0.0)|04:30"}, {"family": "graphicCorner", "class": "CLKComplicationTemplateGraphicCornerStackText", "innerText": "↗2·↗6·04:30", "outerText": "11.1°·87%%"}, {"family": "graphicBezel", "class": "CLKComplicationTemplateGraphicBezelCircularText", "line1": "10.5°", "line2": "11.1°", "text": "Reading 11.1°·87%%·↗2·↗6·04:30"}, {"family": "utilitarianSmall", "class": "CLKComplicationTemplateUtilitarianSmallFlat", "text": "11.1°·87%"}, {"family": "utilitarianLarge", "class": "CLKComplicationTemplateUtilitarianLargeFlat", "text": "Reading 11.1°·87%%·↗2·↗6·04:30"}, {"family": "graphicRectangular", "class": "CLKComplicationTemplateGraphicRectangularStandardBody", "header": "Reading 1012.1hPa↓", "body1": "11.1°|87%%|10.5°|11.1°", "body2": "↗2|↗6|0.0(0.0)|04:30"}]}