{"name": "Reading", "showOnLockScreen": true, "views": [{"type": "text", "body": "Reading 1013.4hPaג†“\n22ֲ°|61%|12.6ֲ°|22ֲ°\nג†–2|ג†–6|0.4(0.0)|14:17"}], "families": [{"family": "graphicCircular", "class": "CLKComplicationTemplateGraphicCircularStackText", "line1": "22ֲ°", "line2": "61%%"}, {"family": "circularSmall", "class": "CLKComplicationTemplateCircularSmallStackText", "line1": "22ֲ°", "line2": "61%"}, {"family": "modularSmall", "class": "CLKComplicationTemplateModularSmallStackText", "line1": "22ֲ°", "line2": "61%"}, {"family": "modularLarge", "class": "CLKComplicationTemplateModularLargeStandardBody", "header": "Reading 1013.4hPaג†“", "body1": "22ֲ°|61%%|12.6ֲ°|22ֲ°", "body2": "ג†–2|ג†–6|0.4(0.0)|14:17"}, {"family": "graphicCorner", "class": "CLKComplicationTemplateGraphicCornerStackText", "innerText": "ג†–2ֲ·ג†–6ֲ·14:17", "outerText": "22ֲ°ֲ·61%%"}, {"family": "graphicBezel", "class": "CLKComplicationTemplateGraphicBezelCircularText", "line1": "12.6ֲ°", "line2": "22ֲ°", "text": "Reading 22ֲ°ֲ·61%%ֲ·ג†–2ֲ·ג†–6ֲ·14:17"}, {"family": "utilitarianSmall", "class": "CLKComplicationTemplateUtilitarianSmallFlat", "text": "22ֲ°ֲ·61%"}, {"family": "utilitarianLarge", "class": "CLKComplicationTemplateUtilitarianLargeFlat", "text": "Reading 22ֲ°ֲ·61%%ֲ·ג†–2ֲ·ג†–6ֲ·14:17"}, {"family": "graphicRectangular", "class": "CLKComplicationTemplateGraphicRectangularStandardBody", "header": "Reading 1013.4hPaג†“", "body1": "22ֲ°|61%%|12.6ֲ°|22ֲ°", "body2": "ג†–2|ג†–6|0.4(0.0)|14:17"}]}