{"name": "Reading", "showOnLockScreen": true, "views": [{"type": "text", "body": "Reading 1019.4hPa↑\n20.5°|75%|13.6°|22.9°\n↗2|↗4|0.6(0.0)|15:28"}], "families": [{"family": "graphicCircular", "class": "CLKComplicationTemplateGraphicCircularStackText", "line1": "20.5°", "line2": "75%%"}, {"family": "circularSmall", "class": "CLKComplicationTemplateCircularSmallStackText", "line1": "20.5°", "line2": "75%"}, {"family": "modularSmall", "class": "CLKComplicationTemplateModularSmallStackText", "line1": "20.5°", "line2": "75%"}, {"family": "modularLarge", "class": "CLKComplicationTemplateModularLargeStandardBody", "header": "Reading 1019.4hPa↑", "body1": "20.5°|75%%|13.6°|22.9°", "body2": "↗2|↗4|0.6(0.0)|15:28"}, {"family": "graphicCorner", "class": "CLKComplicationTemplateGraphicCornerStackText", "innerText": "↗2·↗4·15:28", "outerText": "20.5°·75%%"}, {"family": "graphicBezel", "class": "CLKComplicationTemplateGraphicBezelCircularText", "line1": "13.6°", "line2": "22.9°", "text": "Reading 20.5°·75%%·↗2·↗4·15:28"}, {"family": "utilitarianSmall", "class": "CLKComplicationTemplateUtilitarianSmallFlat", "text": "20.5°·75%"}, {"family": "utilitarianLarge", "class": "CLKComplicationTemplateUtilitarianLargeFlat", "text": "Reading 20.5°·75%%·↗2·↗4·15:28"}, {"family": "graphicRectangular", "class": "CLKComplicationTemplateGraphicRectangularStandardBody", "header": "Reading 1019.4hPa↑", "body1": "20.5°|75%%|13.6°|22.9°", "body2": "↗2|↗4|0.6(0.0)|15:28"}]}