{"name": "Troyan", "showOnLockScreen": true, "views": [{"type": "text", "body": "Троян 1012.5hPa↔\n38.7°|38%|19.4°|38.7°\n↙1|→3|0.0(0.0)|17:02"}], "families": [{"family": "graphicCircular", "class": "CLKComplicationTemplateGraphicCircularStackText", "line1": "38.7°", "line2": "38%%"}, {"family": "circularSmall", "class": "CLKComplicationTemplateCircularSmallStackText", "line1": "38.7°", "line2": "38%"}, {"family": "modularSmall", "class": "CLKComplicationTemplateModularSmallStackText", "line1": "38.7°", "line2": "38%"}, {"family": "modularLarge", "class": "CLKComplicationTemplateModularLargeStandardBody", "header": "Троян 1012.5hPa↔", "body1": "38.7°|38%%|19.4°|38.7°", "body2": "↙1|→3|0.0(0.0)|17:02"}, {"family": "graphicCorner", "class": "CLKComplicationTemplateGraphicCornerStackText", "innerText": "↙1|→3·17:02", "outerText": "38.7°·38%%"}, {"family": "graphicBezel", "class": "CLKComplicationTemplateGraphicBezelCircularText", "line1": "19.4°", "line2": "38.7°", "text": "Троян 38.7°|38%%·↙1|→3·17:02"}, {"family": "utilitarianSmall", "class": "CLKComplicationTemplateUtilitarianSmallFlat", "text": "38.7° 38%"}, {"family": "utilitarianLarge", "class": "CLKComplicationTemplateUtilitarianLargeFlat", "text": "Троян 38.7°|38%%·↙1|→3·17:02"}, {"family": "graphicRectangular", "class": "CLKComplicationTemplateGraphicRectangularStandardBody", "header": "Троян 1012.5hPa↔", "body1": "38.7°|38%%|19.4°|38.7°", "body2": "↙1|→3|0.0(0.0)|17:02"}]}