{"name": "Troyan", "showOnLockScreen": true, "views": [{"type": "text", "body": "Троян 1023.4hPa↔\n6°|73%|3.9°|9.8°\n↘2|↘4|0.0(0.0)|19:35"}], "families": [{"family": "graphicCircular", "class": "CLKComplicationTemplateGraphicCircularStackText", "line1": "6°", "line2": "73%%"}, {"family": "circularSmall", "class": "CLKComplicationTemplateCircularSmallStackText", "line1": "6°", "line2": "73%"}, {"family": "modularSmall", "class": "CLKComplicationTemplateModularSmallStackText", "line1": "6°", "line2": "73%"}, {"family": "modularLarge", "class": "CLKComplicationTemplateModularLargeStandardBody", "header": "Троян 1023.4hPa↔", "body1": "6°|73%%|3.9°|9.8°", "body2": "↘2|↘4|0.0(0.0)|19:35"}, {"family": "graphicCorner", "class": "CLKComplicationTemplateGraphicCornerStackText", "innerText": "↘2|↘4·19:35", "outerText": "6°·73%%"}, {"family": "graphicBezel", "class": "CLKComplicationTemplateGraphicBezelCircularText", "line1": "3.9°", "line2": "9.8°", "text": "Троян 6°|73%%·↘2|↘4·19:35"}, {"family": "utilitarianSmall", "class": "CLKComplicationTemplateUtilitarianSmallFlat", "text": "6° 73%"}, {"family": "utilitarianLarge", "class": "CLKComplicationTemplateUtilitarianLargeFlat", "text": "Троян 6°|73%%·↘2|↘4·19:35"}, {"family": "graphicRectangular", "class": "CLKComplicationTemplateGraphicRectangularStandardBody", "header": "Троян 1023.4hPa↔", "body1": "6°|73%%|3.9°|9.8°", "body2": "↘2|↘4|0.0(0.0)|19:35"}]}