{"name": "Troyan", "showOnLockScreen": true, "views": [{"type": "text", "body": "Троян 1009.1hPa↓\n23.5°|56%|11.4°|23.5°\n→2|→6|0.0(0.0)|12:27"}], "families": [{"family": "graphicCircular", "class": "CLKComplicationTemplateGraphicCircularStackText", "line1": "23.5°", "line2": "56%%"}, {"family": "circularSmall", "class": "CLKComplicationTemplateCircularSmallStackText", "line1": "23.5°", "line2": "56%"}, {"family": "modularSmall", "class": "CLKComplicationTemplateModularSmallStackText", "line1": "23.5°", "line2": "56%"}, {"family": "modularLarge", "class": "CLKComplicationTemplateModularLargeStandardBody", "header": "Троян 1009.1hPa↓", "body1": "23.5°|56%%|11.4°|23.5°", "body2": "→2|→6|0.0(0.0)|12:27"}, {"family": "graphicCorner", "class": "CLKComplicationTemplateGraphicCornerStackText", "innerText": "→2|→6·12:27", "outerText": "23.5°·56%%"}, {"family": "graphicBezel", "class": "CLKComplicationTemplateGraphicBezelCircularText", "line1": "11.4°", "line2": "23.5°", "text": "Троян 23.5°|56%%·→2|→6·12:27"}, {"family": "utilitarianSmall", "class": "CLKComplicationTemplateUtilitarianSmallFlat", "text": "23.5° 56%"}, {"family": "utilitarianLarge", "class": "CLKComplicationTemplateUtilitarianLargeFlat", "text": "Троян 23.5°|56%%·→2|→6·12:27"}, {"family": "graphicRectangular", "class": "CLKComplicationTemplateGraphicRectangularStandardBody", "header": "Троян 1009.1hPa↓", "body1": "23.5°|56%%|11.4°|23.5°", "body2": "→2|→6|0.0(0.0)|12:27"}]}