{"name": "Troyan", "showOnLockScreen": true, "views": [{"type": "text", "body": "Троян 1011.9hPa↑\n9.2°|50%|9.2°|10.9°\n→1|→2|0.0(0.0)|02:43"}], "families": [{"family": "graphicCircular", "class": "CLKComplicationTemplateGraphicCircularStackText", "line1": "9.2°", "line2": "50%%"}, {"family": "circularSmall", "class": "CLKComplicationTemplateCircularSmallStackText", "line1": "9.2°", "line2": "50%"}, {"family": "modularSmall", "class": "CLKComplicationTemplateModularSmallStackText", "line1": "9.2°", "line2": "50%"}, {"family": "modularLarge", "class": "CLKComplicationTemplateModularLargeStandardBody", "header": "Троян 1011.9hPa↑", "body1": "9.2°|50%%|9.2°|10.9°", "body2": "→1|→2|0.0(0.0)|02:43"}, {"family": "graphicCorner", "class": "CLKComplicationTemplateGraphicCornerStackText", "innerText": "→1|→2·02:43", "outerText": "9.2°·50%%"}, {"family": "graphicBezel", "class": "CLKComplicationTemplateGraphicBezelCircularText", "line1": "9.2°", "line2": "10.9°", "text": "Троян 9.2°|50%%·→1|→2·02:43"}, {"family": "utilitarianSmall", "class": "CLKComplicationTemplateUtilitarianSmallFlat", "text": "9.2° 50%"}, {"family": "utilitarianLarge", "class": "CLKComplicationTemplateUtilitarianLargeFlat", "text": "Троян 9.2°|50%%·→1|→2·02:43"}, {"family": "graphicRectangular", "class": "CLKComplicationTemplateGraphicRectangularStandardBody", "header": "Троян 1011.9hPa↑", "body1": "9.2°|50%%|9.2°|10.9°", "body2": "→1|→2|0.0(0.0)|02:43"}]}