{"name": "Troyan", "showOnLockScreen": true, "views": [{"type": "text", "body": "Троян 1013.4hPa↔\n35.2°|43%|19.4°|35.2°\n→1|→5|0.0(0.0)|13:00"}], "families": [{"family": "graphicCircular", "class": "CLKComplicationTemplateGraphicCircularStackText", "line1": "35.2°", "line2": "43%%"}, {"family": "circularSmall", "class": "CLKComplicationTemplateCircularSmallStackText", "line1": "35.2°", "line2": "43%"}, {"family": "modularSmall", "class": "CLKComplicationTemplateModularSmallStackText", "line1": "35.2°", "line2": "43%"}, {"family": "modularLarge", "class": "CLKComplicationTemplateModularLargeStandardBody", "header": "Троян 1013.4hPa↔", "body1": "35.2°|43%%|19.4°|35.2°", "body2": "→1|→5|0.0(0.0)|13:00"}, {"family": "graphicCorner", "class": "CLKComplicationTemplateGraphicCornerStackText", "innerText": "→1|→5·13:00", "outerText": "35.2°·43%%"}, {"family": "graphicBezel", "class": "CLKComplicationTemplateGraphicBezelCircularText", "line1": "19.4°", "line2": "35.2°", "text": "Троян 35.2°|43%%·→1|→5·13:00"}, {"family": "utilitarianSmall", "class": "CLKComplicationTemplateUtilitarianSmallFlat", "text": "35.2° 43%"}, {"family": "utilitarianLarge", "class": "CLKComplicationTemplateUtilitarianLargeFlat", "text": "Троян 35.2°|43%%·→1|→5·13:00"}, {"family": "graphicRectangular", "class": "CLKComplicationTemplateGraphicRectangularStandardBody", "header": "Троян 1013.4hPa↔", "body1": "35.2°|43%%|19.4°|35.2°", "body2": "→1|→5|0.0(0.0)|13:00"}]}