{"name": "Troyan", "showOnLockScreen": true, "views": [{"type": "text", "body": "Троян 1022.1hPa↓\n6.9°|40%|-5.1°|13.1°\n→1|↗3|0.0(0.0)|18:06"}], "families": [{"family": "graphicCircular", "class": "CLKComplicationTemplateGraphicCircularStackText", "line1": "6.9°", "line2": "40%%"}, {"family": "circularSmall", "class": "CLKComplicationTemplateCircularSmallStackText", "line1": "6.9°", "line2": "40%"}, {"family": "modularSmall", "class": "CLKComplicationTemplateModularSmallStackText", "line1": "6.9°", "line2": "40%"}, {"family": "modularLarge", "class": "CLKComplicationTemplateModularLargeStandardBody", "header": "Троян 1022.1hPa↓", "body1": "6.9°|40%%|-5.1°|13.1°", "body2": "→1|↗3|0.0(0.0)|18:06"}, {"family": "graphicCorner", "class": "CLKComplicationTemplateGraphicCornerStackText", "innerText": "→1|↗3·18:06", "outerText": "6.9°·40%%"}, {"family": "graphicBezel", "class": "CLKComplicationTemplateGraphicBezelCircularText", "line1": "-5.1°", "line2": "13.1°", "text": "Троян 6.9°|40%%·→1|↗3·18:06"}, {"family": "utilitarianSmall", "class": "CLKComplicationTemplateUtilitarianSmallFlat", "text": "6.9° 40%"}, {"family": "utilitarianLarge", "class": "CLKComplicationTemplateUtilitarianLargeFlat", "text": "Троян 6.9°|40%%·→1|↗3·18:06"}, {"family": "graphicRectangular", "class": "CLKComplicationTemplateGraphicRectangularStandardBody", "header": "Троян 1022.1hPa↓", "body1": "6.9°|40%%|-5.1°|13.1°", "body2": "→1|↗3|0.0(0.0)|18:06"}]}