{"name": "Troyan", "showOnLockScreen": true, "views": [{"type": "text", "body": "Троян 1011.7hPa↓\n27.6°|57%|11.8°|30.8°\n↑1|↖2|0.0(0.0)|19:30"}], "families": [{"family": "graphicCircular", "class": "CLKComplicationTemplateGraphicCircularStackText", "line1": "27.6°", "line2": "57%%"}, {"family": "circularSmall", "class": "CLKComplicationTemplateCircularSmallStackText", "line1": "27.6°", "line2": "57%"}, {"family": "modularSmall", "class": "CLKComplicationTemplateModularSmallStackText", "line1": "27.6°", "line2": "57%"}, {"family": "modularLarge", "class": "CLKComplicationTemplateModularLargeStandardBody", "header": "Троян 1011.7hPa↓", "body1": "27.6°|57%%|11.8°|30.8°", "body2": "↑1|↖2|0.0(0.0)|19:30"}, {"family": "graphicCorner", "class": "CLKComplicationTemplateGraphicCornerStackText", "innerText": "↑1|↖2", "outerText": "27.6°·57%%"}, {"family": "graphicBezel", "class": "CLKComplicationTemplateGraphicBezelCircularText", "line1": "11.8°", "line2": "30.8°", "text": "Троян 27.6°|57%%·↑1|↖2·19:30"}, {"family": "utilitarianSmall", "class": "CLKComplicationTemplateUtilitarianSmallFlat", "text": "27.6° 57%"}, {"family": "utilitarianLarge", "class": "CLKComplicationTemplateUtilitarianLargeFlat", "text": "Троян 27.6°|57%%·↑1|↖2·19:30"}, {"family": "graphicRectangular", "class": "CLKComplicationTemplateGraphicRectangularStandardBody", "header": "Троян 1011.7hPa↓", "body1": "27.6°|57%%|11.8°|30.8°", "body2": "↑1|↖2|0.0(0.0)|19:30"}]}