{"name": "Troyan", "showOnLockScreen": true, "views": [{"type": "text", "body": "Троян 1023.8hPa↔\n12.7°|66%|3.4°|12.7°\n→2|→6|0.0(0.0)|14:50"}], "families": [{"family": "graphicCircular", "class": "CLKComplicationTemplateGraphicCircularStackText", "line1": "12.7°", "line2": "66%%"}, {"family": "circularSmall", "class": "CLKComplicationTemplateCircularSmallStackText", "line1": "12.7°", "line2": "66%"}, {"family": "modularSmall", "class": "CLKComplicationTemplateModularSmallStackText", "line1": "12.7°", "line2": "66%"}, {"family": "modularLarge", "class": "CLKComplicationTemplateModularLargeStandardBody", "header": "Троян 1023.8hPa↔", "body1": "12.7°|66%%|3.4°|12.7°", "body2": "→2|→6|0.0(0.0)|14:50"}, {"family": "graphicCorner", "class": "CLKComplicationTemplateGraphicCornerStackText", "innerText": "→2|→6·14:50", "outerText": "12.7°·66%%"}, {"family": "graphicBezel", "class": "CLKComplicationTemplateGraphicBezelCircularText", "line1": "3.4°", "line2": "12.7°", "text": "Троян 12.7°|66%%·→2|→6·14:50"}, {"family": "utilitarianSmall", "class": "CLKComplicationTemplateUtilitarianSmallFlat", "text": "12.7° 66%"}, {"family": "utilitarianLarge", "class": "CLKComplicationTemplateUtilitarianLargeFlat", "text": "Троян 12.7°|66%%·→2|→6·14:50"}, {"family": "graphicRectangular", "class": "CLKComplicationTemplateGraphicRectangularStandardBody", "header": "Троян 1023.8hPa↔", "body1": "12.7°|66%%|3.4°|12.7°", "body2": "→2|→6|0.0(0.0)|14:50"}]}